AUTHORS
LICENSE
MANIFEST.in
README.md
TODO.md
setup.py
vmguestlib.py
bin/vmguest-example
bin/vmguest-stats
vmguestlib.egg-info/PKG-INFO
vmguestlib.egg-info/SOURCES.txt
vmguestlib.egg-info/dependency_links.txt
vmguestlib.egg-info/requires.txt
vmguestlib.egg-info/top_level.txt