Metadata-Version: 1.0
Name: vmguestlib
Version: 0.1.2
Summary: Python API for interacting with VMware's VMGuestLib SDK
Home-page: http://github.com/dagwieers/vmguestlib
Author: Dag Wieers
Author-email: dag@wieers.com
License: GPLv2
Download-URL: http://github.com/dagwieers/vmguestlib/archive/0.1.2.tar.gz
Keywords: Virtual,vmware,ESX,ESXi,VMGuestLib,SDK,API
Platform: UNKNOWN
Classifier: Programming Language :: Python
Classifier: Programming Language :: Python :: 2.5
Classifier: Programming Language :: Python :: 2.6
Classifier: Programming Language :: Python :: 2.7
Classifier: Operating System :: OS Independent
Classifier: Development Status :: 5 - Production/Stable
Classifier: Environment :: Other Environment
Classifier: Intended Audience :: Developers
Classifier: Intended Audience :: System Administrators
Classifier: Intended Audience :: Science/Research
Classifier: Intended Audience :: Information Technology
Classifier: License :: OSI Approved :: GNU General Public License v2 or later (GPLv2+)
Classifier: Topic :: Software Development :: Libraries :: Python Modules
Classifier: Topic :: Software Development :: Quality Assurance
Classifier: Topic :: Software Development :: Testing
Classifier: Topic :: System :: Distributed Computing
Classifier: Topic :: System :: Emulators
Classifier: Topic :: System :: Hardware
Classifier: Topic :: System :: Operating System
Classifier: Topic :: System :: Systems Administration
Classifier: Topic :: Utilities
